idom_jupyter/__init__.py
idom_jupyter/_version.py
idom_jupyter/import_resources.py
idom_jupyter/ipython_extension.py
idom_jupyter/jupyter_server_extension.py
idom_jupyter/widget.py
idom_jupyter/labextension/package.json
idom_jupyter/labextension/static/261.c762003e59beb7efa69b.js
idom_jupyter/labextension/static/376.10e9aebd7d3c1d327032.js
idom_jupyter/labextension/static/722.45124f533fb9ea505d53.js
idom_jupyter/labextension/static/722.45124f533fb9ea505d53.js.LICENSE.txt
idom_jupyter/labextension/static/920.3832232bb2c994a0fe5e.js
idom_jupyter/labextension/static/remoteEntry.e775856391cd800fca2c.js
idom_jupyter/labextension/static/style.js
idom_jupyter/labextension/static/third-party-licenses.json
idom_jupyter/nbextension/extension.js
idom_jupyter/nbextension/index.js
idom_jupyter/nbextension/index.js.LICENSE.txt
idom_jupyter-0.7.7.data/data/etc/jupyter/jupyter_notebook_config.d/idom-jupyter.json
idom_jupyter-0.7.7.data/data/etc/jupyter/jupyter_server_config.d/idom-jupyter.json
idom_jupyter-0.7.7.data/data/etc/jupyter/nbconfig/notebook.d/idom-client-jupyter.json
idom_jupyter-0.7.7.data/data/share/jupyter/labextensions/idom-client-jupyter/install.json
idom_jupyter-0.7.7.data/data/share/jupyter/labextensions/idom-client-jupyter/package.json
idom_jupyter-0.7.7.data/data/share/jupyter/labextensions/idom-client-jupyter/static/261.c762003e59beb7efa69b.js
idom_jupyter-0.7.7.data/data/share/jupyter/labextensions/idom-client-jupyter/static/376.10e9aebd7d3c1d327032.js
idom_jupyter-0.7.7.data/data/share/jupyter/labextensions/idom-client-jupyter/static/722.45124f533fb9ea505d53.js
idom_jupyter-0.7.7.data/data/share/jupyter/labextensions/idom-client-jupyter/static/722.45124f533fb9ea505d53.js.LICENSE.txt
idom_jupyter-0.7.7.data/data/share/jupyter/labextensions/idom-client-jupyter/static/920.3832232bb2c994a0fe5e.js
idom_jupyter-0.7.7.data/data/share/jupyter/labextensions/idom-client-jupyter/static/remoteEntry.e775856391cd800fca2c.js
idom_jupyter-0.7.7.dist-info/LICENSE
idom_jupyter-0.7.7.dist-info/METADATA
idom_jupyter-0.7.7.dist-info/WHEEL
idom_jupyter-0.7.7.dist-info/top_level.txt
idom_jupyter-0.7.7.dist-info/RECORD
