Metadata-Version: 2.1
Name: idom-jupyter
Version: 0.7.7
Summary: A client for IDOM implemented using Jupyter widgets
Home-page: https://github.com/idom-team/idom-jupyter
Author: Ryan Morshead
Author-email: ryan.morshead@gmail.com
License: BSD 3-Clause License
Keywords: ipython,jupyter,widgets
Classifier: Development Status :: 4 - Beta
Classifier: Framework :: IPython
Classifier: Intended Audience :: Developers
Classifier: Intended Audience :: Science/Research
Classifier: Topic :: Multimedia :: Graphics
Classifier: Programming Language :: Python :: 3.6
Classifier: Programming Language :: Python :: 3.7
Classifier: Programming Language :: Python :: 3.8
Classifier: Programming Language :: Python :: 3.9
Requires-Python: >=3.7
License-File: LICENSE
Requires-Dist: ipywidgets (>=7.6.0)
Requires-Dist: idom (<0.43,>=0.42)
Requires-Dist: appdirs
Requires-Dist: requests
Requires-Dist: jupyter-server
Requires-Dist: notebook
Requires-Dist: typing-extensions
